library/__init__.py
library/function.py
cppProjectpackage-1.0.0.dist-info/LICENSE
cppProjectpackage-1.0.0.dist-info/METADATA
cppProjectpackage-1.0.0.dist-info/WHEEL
cppProjectpackage-1.0.0.dist-info/top_level.txt
cppProjectpackage-1.0.0.dist-info/RECORD
