Metadata-Version: 2.1
Name: cppProjectpackage
Version: 1.0.0
Summary: A short description of my package
Home-page: https://github.com/my_username/my_package
Author: gauri
Author-email: gauri.21.misra@gmail.com
Classifier: Programming Language :: Python :: 3.11
Classifier: License :: OSI Approved :: MIT License
Classifier: Operating System :: OS Independent
License-File: LICENSE
Requires-Dist: requests (>=2.25.1)
Requires-Dist: numpy (>=1.19.5)
